{
  "generated_at": "2026-02-15T02:20:21.491224+00:00",
  "date": "2025-04-09",
  "picks": [
    {
      "player": "Brown, Hunter",
      "player_id": 686613,
      "opponent": "SEA",
      "player_team": "HOU",
      "home_team": "SEA",
      "away_team": "HOU",
      "market": "Outs Recorded",
      "category": "pitcher",
      "direction": "UNDER",
      "line": 17.5,
      "best_book": "betonlineag",
      "best_price": 145,
      "stars": 3,
      "game_pk": 778383,
      "game_time": null,
      "result": "loss",
      "actual": 18,
      "pnl": -100.0
    },
    {
      "player": "Gausman, Kevin",
      "player_id": 592332,
      "opponent": "BOS",
      "player_team": "TOR",
      "home_team": "BOS",
      "away_team": "TOR",
      "market": "Outs Recorded",
      "category": "pitcher",
      "direction": "UNDER",
      "line": 17.5,
      "best_book": "betonlineag",
      "best_price": 145,
      "stars": 3,
      "game_pk": 778386,
      "game_time": null,
      "result": "loss",
      "actual": 24,
      "pnl": -100.0
    },
    {
      "player": "Keller, Mitch",
      "player_id": 656605,
      "opponent": "STL",
      "player_team": "PIT",
      "home_team": "PIT",
      "away_team": "STL",
      "market": "Outs Recorded",
      "category": "pitcher",
      "direction": "UNDER",
      "line": 17.5,
      "best_book": "draftkings",
      "best_price": 120,
      "stars": 3,
      "game_pk": 778389,
      "game_time": null,
      "result": "loss",
      "actual": 22,
      "pnl": -100.0
    },
    {
      "player": "Pfaadt, Brandon",
      "player_id": 694297,
      "opponent": "BAL",
      "player_team": "AZ",
      "home_team": "AZ",
      "away_team": "BAL",
      "market": "Outs Recorded",
      "category": "pitcher",
      "direction": "UNDER",
      "line": 17.5,
      "best_book": "bovada",
      "best_price": 115,
      "stars": 3,
      "game_pk": 778380,
      "game_time": null,
      "result": "win",
      "actual": 17,
      "pnl": 115.0
    },
    {
      "player": "Chourio, Jackson",
      "player_id": 694192,
      "opponent": "MIL",
      "player_team": "COL",
      "home_team": "COL",
      "away_team": "MIL",
      "market": "Hits",
      "category": "batter",
      "direction": "UNDER",
      "line": 1.5,
      "best_book": "consensus",
      "best_price": -160,
      "stars": 2,
      "game_pk": 778379,
      "game_time": null,
      "result": "loss",
      "actual": 2,
      "pnl": -100.0
    },
    {
      "player": "Contreras, William",
      "player_id": 661388,
      "opponent": "MIL",
      "player_team": "COL",
      "home_team": "COL",
      "away_team": "MIL",
      "market": "Total Bases",
      "category": "batter",
      "direction": "UNDER",
      "line": 1.5,
      "best_book": "consensus",
      "best_price": -109,
      "stars": 2,
      "game_pk": 778379,
      "game_time": null,
      "result": "loss",
      "actual": 4,
      "pnl": -100.0
    },
    {
      "player": "Hoskins, Rhys",
      "player_id": 656555,
      "opponent": "MIL",
      "player_team": "COL",
      "home_team": "COL",
      "away_team": "MIL",
      "market": "Total Bases",
      "category": "batter",
      "direction": "UNDER",
      "line": 1.5,
      "best_book": "consensus",
      "best_price": -123,
      "stars": 2,
      "game_pk": 778379,
      "game_time": null,
      "result": "win",
      "actual": 0,
      "pnl": 81.3
    },
    {
      "player": "Houck, Tanner",
      "player_id": 656557,
      "opponent": "TOR",
      "player_team": "BOS",
      "home_team": "BOS",
      "away_team": "TOR",
      "market": "Outs Recorded",
      "category": "pitcher",
      "direction": "UNDER",
      "line": 17.5,
      "best_book": "draftkings",
      "best_price": -110,
      "stars": 2,
      "game_pk": 778386,
      "game_time": null,
      "result": "loss",
      "actual": 20,
      "pnl": -100.0
    },
    {
      "player": "Lugo, Seth",
      "player_id": 607625,
      "opponent": "MIN",
      "player_team": "KC",
      "home_team": "KC",
      "away_team": "MIN",
      "market": "Outs Recorded",
      "category": "pitcher",
      "direction": "UNDER",
      "line": 17.5,
      "best_book": "betonlineag",
      "best_price": 120,
      "stars": 2,
      "game_pk": 778388,
      "game_time": null,
      "result": "win",
      "actual": 15,
      "pnl": 120.0
    },
    {
      "player": "Pepiot, Ryan",
      "player_id": 686752,
      "opponent": "LAA",
      "player_team": "TB",
      "home_team": "TB",
      "away_team": "LAA",
      "market": "Outs Recorded",
      "category": "pitcher",
      "direction": "UNDER",
      "line": 17.5,
      "best_book": "betonlineag",
      "best_price": -110,
      "stars": 2,
      "game_pk": 778399,
      "game_time": null,
      "result": "win",
      "actual": 15,
      "pnl": 90.91
    },
    {
      "player": "Albies, Ozzie",
      "player_id": 645277,
      "opponent": "PHI",
      "player_team": "ATL",
      "home_team": "ATL",
      "away_team": "PHI",
      "market": "Total Bases",
      "category": "batter",
      "direction": "UNDER",
      "line": 1.5,
      "best_book": "consensus",
      "best_price": -160,
      "stars": 1,
      "game_pk": 778393,
      "game_time": null,
      "result": "win",
      "actual": 1,
      "pnl": 62.5
    },
    {
      "player": "Contreras, William",
      "player_id": 661388,
      "opponent": "MIL",
      "player_team": "COL",
      "home_team": "COL",
      "away_team": "MIL",
      "market": "Hits",
      "category": "batter",
      "direction": "UNDER",
      "line": 1.5,
      "best_book": "consensus",
      "best_price": -192,
      "stars": 1,
      "game_pk": 778379,
      "game_time": null,
      "result": "win",
      "actual": 1,
      "pnl": 52.08
    },
    {
      "player": "D\u00edaz, Yandy",
      "player_id": 650490,
      "opponent": "LAA",
      "player_team": "TB",
      "home_team": "TB",
      "away_team": "LAA",
      "market": "Total Bases",
      "category": "batter",
      "direction": "UNDER",
      "line": 1.5,
      "best_book": "consensus",
      "best_price": -145,
      "stars": 1,
      "game_pk": 778399,
      "game_time": null,
      "result": "loss",
      "actual": 5,
      "pnl": -100.0
    },
    {
      "player": "Fried, Max",
      "player_id": 608331,
      "opponent": "DET",
      "player_team": "NYY",
      "home_team": "DET",
      "away_team": "NYY",
      "market": "Outs Recorded",
      "category": "pitcher",
      "direction": "UNDER",
      "line": 17.5,
      "best_book": "betonlineag",
      "best_price": 135,
      "stars": 1,
      "game_pk": 778387,
      "game_time": null,
      "result": "loss",
      "actual": 21,
      "pnl": -100.0
    },
    {
      "player": "Kikuchi, Yusei",
      "player_id": 579328,
      "opponent": "TB",
      "player_team": "LAA",
      "home_team": "TB",
      "away_team": "LAA",
      "market": "Outs Recorded",
      "category": "pitcher",
      "direction": "UNDER",
      "line": 17.5,
      "best_book": "betonlineag",
      "best_price": 100,
      "stars": 1,
      "game_pk": 778399,
      "game_time": null,
      "result": "loss",
      "actual": 18,
      "pnl": -100.0
    },
    {
      "player": "Knack, Landon",
      "player_id": 689017,
      "opponent": "WSH",
      "player_team": "LAD",
      "home_team": "WSH",
      "away_team": "LAD",
      "market": "Walks",
      "category": "pitcher",
      "direction": "UNDER",
      "line": 1.5,
      "best_book": "draftkings",
      "best_price": 135,
      "stars": 1,
      "game_pk": 778392,
      "game_time": null,
      "result": "loss",
      "actual": 4,
      "pnl": -100.0
    },
    {
      "player": "Mahle, Tyler",
      "player_id": 641816,
      "opponent": "CHC",
      "player_team": "TEX",
      "home_team": "CHC",
      "away_team": "TEX",
      "market": "Strikeouts",
      "category": "pitcher",
      "direction": "UNDER",
      "line": 4.5,
      "best_book": "draftkings",
      "best_price": 115,
      "stars": 1,
      "game_pk": 778385,
      "game_time": null,
      "result": "win",
      "actual": 4,
      "pnl": 115.0
    },
    {
      "player": "Martinez, Nick",
      "player_id": 607259,
      "opponent": "SF",
      "player_team": "CIN",
      "home_team": "SF",
      "away_team": "CIN",
      "market": "Outs Recorded",
      "category": "pitcher",
      "direction": "UNDER",
      "line": 17.5,
      "best_book": "draftkings",
      "best_price": -110,
      "stars": 1,
      "game_pk": 778376,
      "game_time": null,
      "result": "win",
      "actual": 17,
      "pnl": 90.91
    },
    {
      "player": "Mead, Curtis",
      "player_id": 678554,
      "opponent": "LAA",
      "player_team": "TB",
      "home_team": "TB",
      "away_team": "LAA",
      "market": "Total Bases",
      "category": "batter",
      "direction": "UNDER",
      "line": 1.5,
      "best_book": "consensus",
      "best_price": -175,
      "stars": 1,
      "game_pk": 778399,
      "game_time": null,
      "result": "loss",
      "actual": 2,
      "pnl": -100.0
    },
    {
      "player": "Meyer, Max",
      "player_id": 676974,
      "opponent": "NYM",
      "player_team": "MIA",
      "home_team": "NYM",
      "away_team": "MIA",
      "market": "Walks",
      "category": "pitcher",
      "direction": "UNDER",
      "line": 2.5,
      "best_book": "draftkings",
      "best_price": -135,
      "stars": 1,
      "game_pk": 778390,
      "game_time": null,
      "result": "win",
      "actual": 2,
      "pnl": 74.07
    },
    {
      "player": "Pepiot, Ryan",
      "player_id": 686752,
      "opponent": "LAA",
      "player_team": "TB",
      "home_team": "TB",
      "away_team": "LAA",
      "market": "Strikeouts",
      "category": "pitcher",
      "direction": "UNDER",
      "line": 6.5,
      "best_book": "draftkings",
      "best_price": -145,
      "stars": 1,
      "game_pk": 778399,
      "game_time": null,
      "result": "win",
      "actual": 5,
      "pnl": 68.97
    },
    {
      "player": "Ryan, Joe",
      "player_id": 657746,
      "opponent": "KC",
      "player_team": "MIN",
      "home_team": "KC",
      "away_team": "MIN",
      "market": "Outs Recorded",
      "category": "pitcher",
      "direction": "UNDER",
      "line": 17.5,
      "best_book": "draftkings",
      "best_price": -135,
      "stars": 1,
      "game_pk": 778388,
      "game_time": null,
      "result": "loss",
      "actual": 21,
      "pnl": -100.0
    },
    {
      "player": "Yelich, Christian",
      "player_id": 592885,
      "opponent": "MIL",
      "player_team": "COL",
      "home_team": "COL",
      "away_team": "MIL",
      "market": "Hits",
      "category": "batter",
      "direction": "UNDER",
      "line": 1.5,
      "best_book": "consensus",
      "best_price": -214,
      "stars": 1,
      "game_pk": 778379,
      "game_time": null,
      "result": "loss",
      "actual": 2,
      "pnl": -100.0
    },
    {
      "player": "Yelich, Christian",
      "player_id": 592885,
      "opponent": "MIL",
      "player_team": "COL",
      "home_team": "COL",
      "away_team": "MIL",
      "market": "Total Bases",
      "category": "batter",
      "direction": "UNDER",
      "line": 1.5,
      "best_book": "consensus",
      "best_price": -123,
      "stars": 1,
      "game_pk": 778379,
      "game_time": null,
      "result": "loss",
      "actual": 5,
      "pnl": -100.0
    }
  ]
}
