{
  "generated_at": "2026-02-13T16:51:04.519868+00:00",
  "date": "2025-08-07",
  "picks": [
    {
      "player": "Edwards, Xavier",
      "player_id": 669364,
      "opponent": "MIA",
      "player_team": "ATL",
      "home_team": "ATL",
      "away_team": "MIA",
      "market": "Total Bases",
      "category": "batter",
      "direction": "UNDER",
      "line": 1.5,
      "best_book": "fanatics",
      "best_price": -130,
      "stars": 2,
      "game_pk": 776842,
      "result": "loss",
      "actual": 2,
      "pnl": -100.0
    },
    {
      "player": "Gilbert, Logan",
      "player_id": 669302,
      "opponent": "CWS",
      "player_team": "SEA",
      "home_team": "SEA",
      "away_team": "CWS",
      "market": "Outs Recorded",
      "category": "pitcher",
      "direction": "UNDER",
      "line": 18.0,
      "best_book": "draftkings",
      "best_price": 150,
      "stars": 2,
      "game_pk": 776830,
      "result": "win",
      "actual": 15,
      "pnl": 150.0
    },
    {
      "player": "Reynolds, Bryan",
      "player_id": 668804,
      "opponent": "CIN",
      "player_team": "PIT",
      "home_team": "PIT",
      "away_team": "CIN",
      "market": "Total Bases",
      "category": "batter",
      "direction": "UNDER",
      "line": 1.5,
      "best_book": "draftkings",
      "best_price": -135,
      "stars": 2,
      "game_pk": 776840,
      "result": "loss",
      "actual": 5,
      "pnl": -100.0
    },
    {
      "player": "Smith, Shane",
      "player_id": 681343,
      "opponent": "SEA",
      "player_team": "CWS",
      "home_team": "SEA",
      "away_team": "CWS",
      "market": "Outs Recorded",
      "category": "pitcher",
      "direction": "UNDER",
      "line": 14.5,
      "best_book": "fanduel",
      "best_price": 130,
      "stars": 2,
      "game_pk": 776830,
      "result": "loss",
      "actual": 15,
      "pnl": -100.0
    },
    {
      "player": "Skenes, Paul",
      "player_id": 694973,
      "opponent": "CIN",
      "player_team": "PIT",
      "home_team": "PIT",
      "away_team": "CIN",
      "market": "Outs Recorded",
      "category": "pitcher",
      "direction": "UNDER",
      "line": 17.5,
      "best_book": "fanatics",
      "best_price": 130,
      "stars": 1,
      "game_pk": 776840,
      "result": "loss",
      "actual": 18,
      "pnl": -100.0
    }
  ]
}
