{
  "generated_at": "2026-02-15T04:05:21.025896+00:00",
  "date": "2024-04-24",
  "picks": [
    {
      "player": "Anderson, Tyler",
      "player_id": 542881,
      "opponent": "BAL",
      "player_team": "LAA",
      "home_team": "LAA",
      "away_team": "BAL",
      "market": "Outs Recorded",
      "category": "pitcher",
      "direction": "UNDER",
      "line": 17.5,
      "best_book": "draftkings",
      "best_price": -105,
      "stars": 2,
      "game_pk": 746244,
      "game_time": null,
      "result": "win",
      "actual": 15,
      "pnl": 95.24
    },
    {
      "player": "Boyle, Joe",
      "player_id": 671212,
      "opponent": "NYY",
      "player_team": "ATH",
      "home_team": "NYY",
      "away_team": "ATH",
      "market": "Earned Runs",
      "category": "pitcher",
      "direction": "UNDER",
      "line": 2.5,
      "best_book": "draftkings",
      "best_price": -105,
      "stars": 2,
      "game_pk": 745753,
      "game_time": null,
      "result": "win",
      "actual": 2,
      "pnl": 95.24
    },
    {
      "player": "Flaherty, Jack",
      "player_id": 656427,
      "opponent": "TB",
      "player_team": "DET",
      "home_team": "TB",
      "away_team": "DET",
      "market": "Outs Recorded",
      "category": "pitcher",
      "direction": "UNDER",
      "line": 17.5,
      "best_book": "draftkings",
      "best_price": -110,
      "stars": 2,
      "game_pk": 745099,
      "game_time": null,
      "result": "win",
      "actual": 15,
      "pnl": 90.91
    },
    {
      "player": "Lodolo, Nick",
      "player_id": 666157,
      "opponent": "PHI",
      "player_team": "CIN",
      "home_team": "CIN",
      "away_team": "PHI",
      "market": "Outs Recorded",
      "category": "pitcher",
      "direction": "UNDER",
      "line": 16.5,
      "best_book": "consensus",
      "best_price": -103,
      "stars": 2,
      "game_pk": 746725,
      "game_time": null,
      "result": "win",
      "actual": 13,
      "pnl": 97.09
    },
    {
      "player": "L\u00f3pez, Reynaldo",
      "player_id": 625643,
      "opponent": "MIA",
      "player_team": "ATL",
      "home_team": "ATL",
      "away_team": "MIA",
      "market": "Hits Allowed",
      "category": "pitcher",
      "direction": "UNDER",
      "line": 4.5,
      "best_book": "draftkings",
      "best_price": 115,
      "stars": 2,
      "game_pk": 747132,
      "game_time": null,
      "result": "win",
      "actual": 3,
      "pnl": 115.0
    },
    {
      "player": "L\u00f3pez, Reynaldo",
      "player_id": 625643,
      "opponent": "MIA",
      "player_team": "ATL",
      "home_team": "ATL",
      "away_team": "MIA",
      "market": "Walks",
      "category": "pitcher",
      "direction": "UNDER",
      "line": 1.5,
      "best_book": "betmgm",
      "best_price": 125,
      "stars": 2,
      "game_pk": 747132,
      "game_time": null,
      "result": "loss",
      "actual": 2,
      "pnl": -100.0
    },
    {
      "player": "Schmidt, Clarke",
      "player_id": 657376,
      "opponent": "ATH",
      "player_team": "NYY",
      "home_team": "NYY",
      "away_team": "ATH",
      "market": "Outs Recorded",
      "category": "pitcher",
      "direction": "UNDER",
      "line": 16.5,
      "best_book": "draftkings",
      "best_price": 100,
      "stars": 2,
      "game_pk": 745753,
      "game_time": null,
      "result": "win",
      "actual": 16,
      "pnl": 100.0
    },
    {
      "player": "Gibson, Kyle",
      "player_id": 502043,
      "opponent": "AZ",
      "player_team": "STL",
      "home_team": "STL",
      "away_team": "AZ",
      "market": "Outs Recorded",
      "category": "pitcher",
      "direction": "UNDER",
      "line": 17.5,
      "best_book": "draftkings",
      "best_price": 145,
      "stars": 1,
      "game_pk": 745188,
      "game_time": null,
      "result": "loss",
      "actual": 18,
      "pnl": -100.0
    }
  ]
}
