{
  "generated_at": "2026-02-13T18:51:50.752464+00:00",
  "date": "2024-04-11",
  "picks": [
    {
      "player": "Gray, Jon",
      "player_id": 592351,
      "opponent": "ATH",
      "player_team": "TEX",
      "home_team": "TEX",
      "away_team": "ATH",
      "market": "Outs Recorded",
      "category": "pitcher",
      "direction": "UNDER",
      "line": 17.5,
      "best_book": "williamhill_us",
      "best_price": -117,
      "stars": 3,
      "game_pk": 745029,
      "result": "win",
      "actual": 15,
      "pnl": 85.47,
      "game_time": "2:35 PM ET"
    },
    {
      "player": "Sears, JP",
      "player_id": 676664,
      "opponent": "TEX",
      "player_team": "ATH",
      "home_team": "TEX",
      "away_team": "ATH",
      "market": "Outs Recorded",
      "category": "pitcher",
      "direction": "UNDER",
      "line": 16.5,
      "best_book": "draftkings",
      "best_price": 100,
      "stars": 2,
      "game_pk": 745029,
      "result": "loss",
      "actual": 19,
      "pnl": -100.0,
      "game_time": "2:35 PM ET"
    },
    {
      "player": "Quintana, Jose",
      "player_id": 500779,
      "opponent": "ATL",
      "player_team": "NYM",
      "home_team": "ATL",
      "away_team": "NYM",
      "market": "Earned Runs",
      "category": "pitcher",
      "direction": "UNDER",
      "line": 3.5,
      "best_book": "draftkings",
      "best_price": -135,
      "stars": 1,
      "game_pk": 747137,
      "result": "win",
      "actual": 3,
      "pnl": 74.07,
      "game_time": "12:20 PM ET"
    },
    {
      "player": "Quintana, Jose",
      "player_id": 500779,
      "opponent": "ATL",
      "player_team": "NYM",
      "home_team": "ATL",
      "away_team": "NYM",
      "market": "Outs Recorded",
      "category": "pitcher",
      "direction": "UNDER",
      "line": 16.5,
      "best_book": "draftkings",
      "best_price": -130,
      "stars": 1,
      "game_pk": 747137,
      "result": "win",
      "actual": 16,
      "pnl": 76.92,
      "game_time": "12:20 PM ET"
    },
    {
      "player": "Rodriguez, Grayson",
      "player_id": 680570,
      "opponent": "BOS",
      "player_team": "BAL",
      "home_team": "BOS",
      "away_team": "BAL",
      "market": "Outs Recorded",
      "category": "pitcher",
      "direction": "UNDER",
      "line": 17.5,
      "best_book": "draftkings",
      "best_price": 100,
      "stars": 1,
      "game_pk": 746977,
      "result": "win",
      "actual": 17,
      "pnl": 100.0,
      "game_time": "7:10 PM ET"
    },
    {
      "player": "Singer, Brady",
      "player_id": 663903,
      "opponent": "HOU",
      "player_team": "KC",
      "home_team": "KC",
      "away_team": "HOU",
      "market": "Outs Recorded",
      "category": "pitcher",
      "direction": "UNDER",
      "line": 17.5,
      "best_book": "draftkings",
      "best_price": 115,
      "stars": 1,
      "game_pk": 746322,
      "result": "win",
      "actual": 15,
      "pnl": 115.0,
      "game_time": "2:10 PM ET"
    }
  ]
}
